substrait/_version.py
substrait/bimap.py
substrait/derivation_expression.py
substrait/simple_extension_utils.py
substrait/type_inference.py
substrait/version.py
substrait/builders/__init__.py
substrait/builders/extended_expression.py
substrait/builders/plan.py
substrait/builders/type.py
substrait/dataframe/__init__.py
substrait/dataframe/dataframe.py
substrait/dataframe/expression.py
substrait/extension_files/__init__.py
substrait/extension_files/extension_types.yaml
substrait/extension_files/functions_aggregate_approx.yaml
substrait/extension_files/functions_aggregate_decimal_output.yaml
substrait/extension_files/functions_aggregate_generic.yaml
substrait/extension_files/functions_arithmetic.yaml
substrait/extension_files/functions_arithmetic_decimal.yaml
substrait/extension_files/functions_boolean.yaml
substrait/extension_files/functions_comparison.yaml
substrait/extension_files/functions_datetime.yaml
substrait/extension_files/functions_geometry.yaml
substrait/extension_files/functions_list.yaml
substrait/extension_files/functions_logarithmic.yaml
substrait/extension_files/functions_rounding.yaml
substrait/extension_files/functions_rounding_decimal.yaml
substrait/extension_files/functions_set.yaml
substrait/extension_files/functions_string.yaml
substrait/extension_files/type_variations.yaml
substrait/extension_files/unknown.yaml
substrait/extension_registry/__init__.py
substrait/extension_registry/exceptions.py
substrait/extension_registry/function_entry.py
substrait/extension_registry/registry.py
substrait/extension_registry/signature_checker_helpers.py
substrait/gen/__init__.py
substrait/gen/__init__.pyi
substrait/gen/antlr/SubstraitTypeLexer.py
substrait/gen/antlr/SubstraitTypeListener.py
substrait/gen/antlr/SubstraitTypeParser.py
substrait/gen/antlr/__init__.py
substrait/gen/antlr/__init__.pyi
substrait/gen/json/__init__.py
substrait/gen/json/__init__.pyi
substrait/gen/json/simple_extensions.py
substrait/proto/__init__.py
substrait/sql/sql_to_substrait.py
substrait-0.27.0.dist-info/licenses/LICENSE
substrait-0.27.0.dist-info/METADATA
substrait-0.27.0.dist-info/WHEEL
substrait-0.27.0.dist-info/top_level.txt
substrait-0.27.0.dist-info/RECORD
