Metadata-Version: 2.4
Name: substrait
Version: 0.27.0
Summary: A python package for Substrait.
Author-email: Substrait contributors <substrait@googlegroups.com>
License: Apache-2.0
Requires-Python: <3.14,>=3.10
License-File: LICENSE
Requires-Dist: protobuf<7,>=5
Requires-Dist: substrait-protobuf==0.79.0
Provides-Extra: extensions
Requires-Dist: antlr4-python3-runtime; extra == "extensions"
Requires-Dist: pyyaml; extra == "extensions"
Provides-Extra: sql
Requires-Dist: sqloxide; extra == "sql"
Requires-Dist: deepdiff; extra == "sql"
Dynamic: license-file
